wavesql/aio.py
wavesql/asyncdatabase.py
wavesql/config.ini
wavesql/constants.py
wavesql/database.py
wavesql/errors.py
wavesql/sqlFileObject.py
wavesql/sync.py
wavesql/python/aio.py
wavesql/python/asyncdatabase.py
wavesql/python/database.py
wavesql/python/sync.py
wavesql/sql/-1_init_logs.sql
wavesql/sql/-2_init_db.sql
wavesql-1.0.5.dist-info/licenses/LICENSE
wavesql-1.0.5.dist-info/licenses/NOTICE
wavesql-1.0.5.dist-info/METADATA
wavesql-1.0.5.dist-info/WHEEL
wavesql-1.0.5.dist-info/top_level.txt
wavesql-1.0.5.dist-info/RECORD
