Metadata-Version: 2.4
Name: WaveSQL
Version: 1.0.5
Summary: SQL helper for databases
Author-email: Darov Alexander Rostislavovich <darov-alexander@outlook.com>
Maintainer-email: "eelus1ve (Darov Alexander)" <darov-alexander@outlook.com>
License-Expression: Apache-2.0
Project-URL: homepage, https://github.com/WaveTeamDevs/WaveSQL
Project-URL: repository, https://github.com/WaveTeamDevs/WaveSQL
Project-URL: bug-tracker, https://github.com/WaveTeamDevs/WaveSQL/issues
Project-URL: organization, https://github.com/WaveTeamDevs
Project-URL: author-profile, https://github.com/eelus1ve
Requires-Python: >=3.12
License-File: LICENSE
License-File: NOTICE
Requires-Dist: mysql-connector-python==9.3.0
Requires-Dist: colorama==0.4.6
Dynamic: license-file
